blink/blink.v
// Blink an LED on the iCEBreaker (iCE40UP5K).
// 12 MHz clock -> counter -> top bit drives the LED.

module blink (
    input  wire clk,      // 12 MHz oscillator
    output wire led        // active-low green LED (LEDG_N)
);
    reg [23:0] counter = 0;

    always @(posedge clk)
        counter <= counter + 1'b1;

    // ~12e6 / 2^24 ≈ 0.7 Hz toggle. Active-low LED, so invert.
    assign led = ~counter[23];
endmodule

latchup-problems/blink/blink_tb.v
`timescale 1ns/1ps
module blink_tb;
    reg clk = 0;
    wire led;

    // Shrink the counter idea by just clocking fast and watching a low bit.
    blink dut (.clk(clk), .led(led));

    always #41.667 clk = ~clk;   // 12 MHz -> period 83.33 ns

    initial begin
        $dumpfile("blink.vcd");
        $dumpvars(0, blink_tb);
        #2_000_000;               // run 2 ms of sim time
        $finish;
    end
endmodule

latchup-problems/blink/blink.vcd
$date
	Fri Jun 26 15:58:24 2026
$end
$version
	Icarus Verilog
$end
$timescale
	1ps
$end
$scope module blink_tb $end
$var wire 1 ! led $end
$var reg 1 " clk $end
$scope module dut $end
$var wire 1 " clk $end
$var wire 1 ! led $end
$var reg 24 # counter [23:0] $end
$upscope $end
$upscope $end
$enddefinitions $end
$comment Show the parameter values. $end
$dumpall
$end
#0
$dumpvars
b0 #
0"
1!
$end
#41667
b1 #
1"
#83334
0"
#125001
b10 #
1"
#166668
0"
#208335
b11 #
1"
#250002
0"
#291669
b100 #
1"
#333336
0"
#375003
b101 #
1"
#416670
0"
#458337
b110 #
1"
#500004
0"
#541671
b111 #
1"
#583338
0"
#625005
b1000 #
1"
#666672
0"
#708339
b1001 #
1"
#750006
0"
#791673
b1010 #
1"
#833340
0"
#875007
b1011 #
1"
#916674
0"
#958341
b1100 #
1"
#1000008
0"
#1041675
b1101 #
1"
#1083342
0"
#1125009
b1110 #
1"
#1166676
0"
#1208343
b1111 #
1"
#1250010
0"
#1291677
b10000 #
1"
#1333344
0"
#1375011
b10001 #
1"
#1416678
0"
#1458345
b10010 #
1"
#1500012
0"
#1541679
b10011 #
1"
#1583346
0"
#1625013
b10100 #
1"
#1666680
0"
#1708347
b10101 #
1"
#1750014
0"
#1791681
b10110 #
1"
#1833348
0"
#1875015
b10111 #
1"
#1916682
0"
#1958349
b11000 #
1"
#2000016
0"
#2041683
b11001 #
1"
#2083350
0"
#2125017
b11010 #
1"
#2166684
0"
#2208351
b11011 #
1"
#2250018
0"
#2291685
b11100 #
1"
#2333352
0"
#2375019
b11101 #
1"
#2416686
0"
#2458353
b11110 #
1"
#2500020
0"
#2541687
b11111 #
1"
#2583354
0"
#2625021
b100000 #
1"
#2666688
0"
#2708355
b100001 #
1"
#2750022
0"
#2791689
b100010 #
1"
#2833356
0"
#2875023
b100011 #
1"
#2916690
0"
#2958357
b100100 #
1"
#3000024
0"
#3041691
b100101 #
1"
#3083358
0"
#3125025
b100110 #
1"
#3166692
0"
#3208359
b100111 #
1"
#3250026
0"
#3291693
b101000 #
1"
#3333360
0"
#3375027
b101001 #
1"
#3416694
0"
#3458361
b101010 #
1"
#3500028
0"
#3541695
b101011 #
1"
#3583362
0"
#3625029
b101100 #
1"
#3666696
0"
#3708363
b101101 #
1"
#3750030
0"
#3791697
b101110 #
1"
#3833364
0"
#3875031
b101111 #
1"
#3916698
0"
#3958365
b110000 #
1"
#4000032
0"
#4041699
b110001 #
1"
#4083366
0"
#4125033
b110010 #
1"
#4166700
0"
#4208367
b110011 #
1"
#4250034
0"
#4291701
b110100 #
1"
#4333368
0"
#4375035
b110101 #
1"
#4416702
0"
#4458369
b110110 #
1"
#4500036
0"
#4541703
b110111 #
1"
#4583370
0"
#4625037
b111000 #
1"
#4666704
0"
#4708371
b111001 #
1"
#4750038
0"
#4791705
b111010 #
1"
#4833372
0"
#4875039
b111011 #
1"
#4916706
0"
#4958373
b111100 #
1"
#5000040
0"
#5041707
b111101 #
1"
#5083374
0"
#5125041
b111110 #
1"
#5166708
0"
#5208375
b111111 #
1"
#5250042
0"
#5291709
b1000000 #
1"
#5333376
0"
#5375043
b1000001 #
1"
#5416710
0"
#5458377
b1000010 #
1"
#5500044
0"
#5541711
b1000011 #
1"
#5583378
0"
#5625045
b1000100 #
1"
#5666712
0"
#5708379
b1000101 #
1"
#5750046
0"
#5791713
b1000110 #
1"
#5833380
0"
#5875047
b1000111 #
1"
#5916714
0"
#5958381
b1001000 #
1"
#6000048
0"
#6041715
b1001001 #
1"
#6083382
0"
#6125049
b1001010 #
1"
#6166716
0"
#6208383
b1001011 #
1"
#6250050
0"
#6291717
b1001100 #
1"
#6333384
0"
#6375051
b1001101 #
1"
#6416718
0"
#6458385
b1001110 #
1"
#6500052
0"
#6541719
b1001111 #
1"
#6583386
0"
#6625053
b1010000 #
1"
#6666720
0"
#6708387
b1010001 #
1"
#6750054
0"
#6791721
b1010010 #
1"
#6833388
0"
#6875055
b1010011 #
1"
#6916722
0"
#6958389
b1010100 #
1"
#7000056
0"
#7041723
b1010101 #
1"
#7083390
0"
#7125057
b1010110 #
1"
#7166724
0"
#7208391
b1010111 #
1"
#7250058
0"
#7291725
b1011000 #
1"
#7333392
0"
#7375059
b1011001 #
1"
#7416726
0"
#7458393
b1011010 #
1"
#7500060
0"
#7541727
b1011011 #
1"
#7583394
0"
#7625061
b1011100 #
1"
#7666728
0"
#7708395
b1011101 #
1"
#7750062
0"
#7791729
b1011110 #
1"
#7833396
0"
#7875063
b1011111 #
1"
#7916730
0"
#7958397
b1100000 #
1"
#8000064
0"
#8041731
b1100001 #
1"
#8083398
0"
#8125065
b1100010 #
1"
#8166732
0"
#8208399
b1100011 #
1"
#8250066
0"
#8291733
b1100100 #
1"
#8333400
0"
#8375067
b1100101 #
1"
#8416734
0"
#8458401
b1100110 #
1"
#8500068
0"
#8541735
b1100111 #
1"
#8583402
0"
#8625069
b1101000 #
1"
#8666736
0"
#8708403
b1101001 #
1"
#8750070
0"
#8791737
b1101010 #
1"
#8833404
0"
#8875071
b1101011 #
1"
#8916738
0"
#8958405
b1101100 #
1"
#9000072
0"
#9041739
b1101101 #
1"
#9083406
0"
#9125073
b1101110 #
1"
#9166740
0"
#9208407
b1101111 #
1"
#9250074
0"
#9291741
b1110000 #
1"
#9333408
0"
#9375075
b1110001 #
1"
#9416742
0"
#9458409
b1110010 #
1"
#9500076
0"
#9541743
b1110011 #
1"
#9583410
0"
#9625077
b1110100 #
1"
#9666744
0"
#9708411
b1110101 #
1"
#9750078
0"
#9791745
b1110110 #
1"
#9833412
0"
#9875079
b1110111 #
1"
#9916746
0"
#9958413
b1111000 #
1"
#10000080
0"
#10041747
b1111001 #
1"
#10083414
0"
#10125081
b1111010 #
1"
#10166748
0"
#10208415
b1111011 #
1"
#10250082
0"
#10291749
b1111100 #
1"
#10333416
0"
#10375083
b1111101 #
1"
#10416750
0"
#10458417
b1111110 #
1"
#10500084
0"
#10541751
b1111111 #
1"
#10583418
0"
#10625085
b10000000 #
1"
#10666752
0"
#10708419
b10000001 #
1"
#10750086
0"
#10791753
b10000010 #
1"
#10833420
0"
#10875087
b10000011 #
1"
#10916754
0"
#10958421
b10000100 #
1"
#11000088
0"
#11041755
b10000101 #
1"
#11083422
0"
#11125089
b10000110 #
1"
#11166756
0"
#11208423
b10000111 #
1"
#11250090
0"
#11291757
b10001000 #
1"
#11333424
0"
#11375091
b10001001 #
1"
#11416758
0"
#11458425
b10001010 #
1"
#11500092
0"
#11541759
b10001011 #
1"
#11583426
0"
#11625093
b10001100 #
1"
#11666760
0"
#11708427
b10001101 #
1"
#11750094
0"
#11791761
b10001110 #
1"
#11833428
0"
#11875095
b10001111 #
1"
#11916762
0"
#11958429
b10010000 #
1"
#12000096
0"
#12041763
b10010001 #
1"
#12083430
0"
#12125097
b10010010 #
1"
#12166764
0"
#12208431
b10010011 #
1"
#12250098
0"
#12291765
b10010100 #
1"
#12333432
0"
#12375099
b10010101 #
1"
#12416766
0"
#12458433
b10010110 #
1"
#12500100
0"
#12541767
b10010111 #
1"
#12583434
0"
#12625101
b10011000 #
1"
#12666768
0"
#12708435
b10011001 #
1"
#12750102
0"
#12791769
b10011010 #
1"
#12833436
0"
#12875103
b10011011 #
1"
#12916770
0"
#12958437
b10011100 #
1"
#13000104
0"
#13041771
b10011101 #
1"
#13083438
0"
#13125105
b10011110 #
1"
#13166772
0"
#13208439
b10011111 #
1"
#13250106
0"
#13291773
b10100000 #
1"
#13333440
0"
#13375107
b10100001 #
1"
#13416774
0"
#13458441
b10100010 #
1"
#13500108
0"
#13541775
b10100011 #
1"
#13583442
0"
#13625109
b10100100 #
1"
#13666776
0"
#13708443
b10100101 #
1"
#13750110
0"
#13791777
b10100110 #
1"
#13833444
0"
#13875111
b10100111 #
1"
#13916778
0"
#13958445
b10101000 #
1"
#14000112
0"
#14041779
b10101001 #
1"
#14083446
0"
#14125113
b10101010 #
1"
#14166780
0"
#14208447
b10101011 #
1"
#14250114
0"
#14291781
b10101100 #
1"
#14333448
0"
#14375115
b10101101 #
1"
#14416782
0"
#14458449
b10101110 #
1"
#14500116
0"
#14541783
b10101111 #
1"
#14583450
0"
#14625117
b10110000 #
1"
#14666784
0"
#14708451
b10110001 #
1"
#14750118
0"
#14791785
b10110010 #
1"
#14833452
0"
#14875119
b10110011 #
1"
#14916786
0"
#14958453
b10110100 #
1"
#15000120
0"
#15041787
b10110101 #
1"
#15083454
0"
#15125121
b10110110 #
1"
#15166788
0"
#15208455
b10110111 #
1"
#15250122
0"
#15291789
b10111000 #
1"
#15333456
0"
#15375123
b10111001 #
1"
#15416790
0"
#15458457
b10111010 #
1"
#15500124
0"
#15541791
b10111011 #
1"
#15583458
0"
#15625125
b10111100 #
1"
#15666792
0"
#15708459
b10111101 #
1"
#15750126
0"
#15791793
b10111110 #
1"
#15833460
0"
#15875127
b10111111 #
1"
#15916794
0"
#15958461
b11000000 #
1"
#16000128
0"
#16041795
b11000001 #
1"
#16083462
0"
#16125129
b11000010 #
1"
#16166796
0"
#16208463
b11000011 #
1"
#16250130
0"
#16291797
b11000100 #
1"
#16333464
0"
#16375131
b11000101 #
1"
#16416798
0"
#16458465
b11000110 #
1"
#16500132
0"
#16541799
b11000111 #
1"
#16583466
0"
#16625133
b11001000 #
1"
#16666800
0"
#16708467
b11001001 #
1"
#16750134
0"
#16791801
b11001010 #
1"
#16833468
0"
#16875135
b11001011 #
1"
#16916802
0"
#16958469
b11001100 #
1"
#17000136
0"
#17041803
b11001101 #
1"
#17083470
0"
#17125137
b11001110 #
1"
#17166804
0"
#17208471
b11001111 #
1"
#17250138
0"
#17291805
b11010000 #
1"
#17333472
0"
#17375139
b11010001 #
1"
#17416806
0"
#17458473
b11010010 #
1"
#17500140
0"
#17541807
b11010011 #
1"
#17583474
0"
#17625141
b11010100 #
1"
#17666808
0"
#17708475
b11010101 #
1"
#17750142
0"
#17791809
b11010110 #
1"
#17833476
0"
#17875143
b11010111 #
1"
#17916810
0"
#17958477
b11011000 #
1"
#18000144
0"
#18041811
b11011001 #
1"
#18083478
0"
#18125145
b11011010 #
1"
#18166812
0"
#18208479
b11011011 #
1"
#18250146
0"
#18291813
b11011100 #
1"
#18333480
0"
#18375147
b11011101 #
1"
#18416814
0"
#18458481
b11011110 #
1"
#18500148
0"
#18541815
b11011111 #
1"
#18583482
0"
#18625149
b11100000 #
1"
#18666816
0"
#18708483
b11100001 #
1"
#18750150
0"
#18791817
b11100010 #
1"
#18833484
0"
#18875151
b11100011 #
1"
#18916818
0"
#18958485
b11100100 #
1"
#19000152
0"
#19041819
b11100101 #
1"
#19083486
0"
#19125153
b11100110 #
1"
#19166820
0"
#19208487
b11100111 #
1"
#19250154
0"
#19291821
b11101000 #
1"
#19333488
0"
#19375155
b11101001 #
1"
#19416822
0"
#19458489
b11101010 #
1"
#19500156
0"
#19541823
b11101011 #
1"
#19583490
0"
#19625157
b11101100 #
1"
#19666824
0"
#19708491
b11101101 #
1"
#19750158
0"
#19791825
b11101110 #
1"
#19833492
0"
#19875159
b11101111 #
1"
#19916826
0"
#19958493
b11110000 #
1"
#20000160
0"
#20041827
b11110001 #
1"
#20083494
0"
#20125161
b11110010 #
1"
#20166828
0"
#20208495
b11110011 #
1"
#20250162
0"
#20291829
b11110100 #
1"
#20333496
0"
#20375163
b11110101 #
1"
#20416830
0"
#20458497
b11110110 #
1"
#20500164
0"
#20541831
b11110111 #
1"
#20583498
0"
#20625165
b11111000 #
1"
#20666832
0"
#20708499
b11111001 #
1"
#20750166
0"
#20791833
b11111010 #
1"
#20833500
0"
#20875167
b11111011 #
1"
#20916834
0"
#20958501
b11111100 #
1"
#21000168
0"
#21041835
b11111101 #
1"
#21083502
0"
#21125169
b11111110 #
1"
#21166836
0"
#21208503
b11111111 #
1"
#21250170
0"
#21291837
b100000000 #
1"
#21333504
0"
#21375171
b100000001 #
1"
#21416838
0"
#21458505
b100000010 #
1"
#21500172
0"
#21541839
b100000011 #
1"
#21583506
0"
#21625173
b100000100 #
1"
#21666840
0"
#21708507
b100000101 #
1"
#21750174
0"
#21791841
b100000110 #
1"
#21833508
0"
#21875175
b100000111 #
1"
#21916842
0"
#21958509
b100001000 #
1"
#22000176
0"
#22041843
b100001001 #
1"
#22083510
0"
#22125177
b100001010 #
1"
#22166844
0"
#22208511
b100001011 #
1"
#22250178
0"
#22291845
b100001100 #
1"
#22333512
0"
#22375179
b100001101 #
1"
#22416846
0"
#22458513
b100001110 #
1"
#22500180
0"
#22541847
b100001111 #
1"
#22583514
0"
#22625181
b100010000 #
1"
#22666848
0"
#22708515
b100010001 #
1"
#22750182
0"
#22791849
b100010010 #
1"
#22833516
0"
#22875183
b100010011 #
1"
#22916850
0"
#22958517
b100010100 #
1"
#23000184
0"
#23041851
b100010101 #
1"
#23083518
0"
#23125185
b100010110 #
1"
#23166852
0"
#23208519
b100010111 #
1"
#23250186
0"
#23291853
b100011000 #
1"
#23333520
0"
#23375187
b100011001 #
1"
#23416854
0"
#23458521
b100011010 #
1"
#23500188
0"
#23541855
b100011011 #
1"
#23583522
0"
#23625189
b100011100 #
1"
#23666856
0"
#23708523
b100011101 #
1"
#23750190
0"
#23791857
b100011110 #
1"
#23833524
0"
#23875191
b100011111 #
1"
#23916858
0"
#23958525
b100100000 #
1"
#24000192
0"
#24041859
b100100001 #
1"
#24083526
0"
#24125193
b100100010 #
1"
#24166860
0"
#24208527
b100100011 #
1"
#24250194
0"
#24291861
b100100100 #
1"
#24333528
0"
#24375195
b100100101 #
1"
#24416862
0"
#24458529
b100100110 #
1"
#24500196
0"
#24541863
b100100111 #
1"
#24583530
0"
#24625197
b100101000 #
1"
#24666864
0"
#24708531
b100101001 #
1"
#24750198
0"
#24791865
b100101010 #
1"
#24833532
0"
#24875199
b100101011 #
1"
#24916866
0"
#24958533
b100101100 #
1"
#25000200
0"
#25041867
b100101101 #
1"
#25083534
0"
#25125201
b100101110 #
1"
#25166868
0"
#25208535
b100101111 #
1"
#25250202
0"
#25291869
b100110000 #
1"
#25333536
0"
#25375203
b100110001 #
1"
#25416870
0"
#25458537
b100110010 #
1"
#25500204
0"
#25541871
b100110011 #
1"
#25583538
0"
#25625205
b100110100 #
1"
#25666872
0"
#25708539
b100110101 #
1"
#25750206
0"
#25791873
b100110110 #
1"
#25833540
0"
#25875207
b100110111 #
1"
#25916874
0"
#25958541
b100111000 #
1"
#26000208
0"
#26041875
b100111001 #
1"
#26083542
0"
#26125209
b100111010 #
1"
#26166876
0"
#26208543
b100111011 #
1"
#26250210
0"
#26291877
b100111100 #
1"
#26333544
0"
#26375211
b100111101 #
1"
#26416878
0"
#26458545
b100111110 #
1"
#26500212
0"
#26541879
b100111111 #
1"
#26583546
0"
#26625213
b101000000 #
1"
#26666880
0"
#26708547
b101000001 #
1"
#26750214
0"
#26791881
b101000010 #
1"
#26833548
0"
#26875215
b101000011 #
1"
#26916882
0"
#26958549
b101000100 #
1"
#27000216
0"
#27041883
b101000101 #
1"
#27083550
0"
#27125217
b101000110 #
1"
#27166884
0"
#27208551
b101000111 #
1"
#27250218
0"
#27291885
b101001000 #
1"
#27333552
0"
#27375219
b101001001 #
1"
#27416886
0"
#27458553
b101001010 #
1"
#27500220
0"
#27541887
b101001011 #
1"
#27583554
0"
#27625221
b101001100 #
1"
#27666888
0"
#27708555
b101001101 #
1"
#27750222
0"
#27791889
b101001110 #
1"
#27833556
0"
#27875223
b101001111 #
1"
#27916890
0"
#27958557
b101010000 #
1"
#28000224
0"
#28041891
b101010001 #
1"
#28083558
0"
#28125225
b101010010 #
1"
#28166892
0"
#28208559
b101010011 #
1"
#28250226
0"
#28291893
b101010100 #
1"
#28333560
0"
#28375227
b101010101 #
1"
#28416894
0"
#28458561
b101010110 #
1"
#28500228
0"
#28541895
b101010111 #
1"
#28583562
0"
#28625229
b101011000 #
1"
#28666896
0"
#28708563
b101011001 #
1"
#28750230
0"
#28791897
b101011010 #
1"
#28833564
0"
#28875231
b101011011 #
1"
#28916898
0"
#28958565
b101011100 #
1"
#29000232
0"
#29041899
b101011101 #
1"
#29083566
0"
#29125233
b101011110 #
1"
#29166900
0"
#29208567
b101011111 #
1"
#29250234
0"
#29291901
b101100000 #
1"
#29333568
0"
#29375235
b101100001 #
1"
#29416902
0"
#29458569
b101100010 #
1"
#29500236
0"
#29541903
b101100011 #
1"
#29583570
0"
#29625237
b101100100 #
1"
#29666904
0"
#29708571
b101100101 #
1"
#29750238
0"
#29791905
b101100110 #
1"
#29833572
0"
#29875239
b101100111 #
1"
#29916906
0"
#29958573
b101101000 #
1"
#30000240
0"
#30041907
b101101001 #
1"
#30083574
0"
#30125241
b101101010 #
1"
#30166908
0"
#30208575
b101101011 #
1"
#30250242
0"
#30291909
b101101100 #
1"
#30333576
0"
#30375243
b101101101 #
1"
#30416910
0"
#30458577
b101101110 #
1"
#30500244
0"
#30541911
b101101111 #
1"
#30583578
0"
#30625245
b101110000 #
1"
#30666912
0"
#30708579
b101110001 #
1"
#30750246
0"
#30791913
b101110010 #
1"
#30833580
0"
#30875247
b101110011 #
1"
#30916914
0"
#30958581
b101110100 #
1"
#31000248
0"
#31041915
b101110101 #
1"
#31083582
0"
#31125249
b101110110 #
1"
#31166916
0"
#31208583
b101110111 #
1"
#31250250
0"
#31291917
b101111000 #
1"
#31333584
0"
#31375251
b101111001 #
1"
#31416918
0"
#31458585
b101111010 #
1"
#31500252
0"
#31541919
b101111011 #
1"
#31583586
0"
#31625253
b101111100 #
1"
#31666920
0"
#31708587
b101111101 #
1"
#31750254
0"
#31791921
b101111110 #
1"
#31833588
0"
#31875255
b101111111 #
1"
#31916922
0"
#31958589
b110000000 #
1"
#32000256
0"
#32041923
b110000001 #
1"
#32083590
0"
#32125257
b110000010 #
1"
#32166924
0"
#32208591
b110000011 #
1"
#32250258
0"
#32291925
b110000100 #
1"
#32333592
0"
#32375259
b110000101 #
1"
#32416926
0"
#32458593
b110000110 #
1"
#32500260
0"
#32541927
b110000111 #
1"
#32583594
0"
#32625261
b110001000 #
1"
#32666928
0"
#32708595
b110001001 #
1"
#32750262
0"
#32791929
b110001010 #
1"
#32833596
0"
#32875263
b110001011 #
1"
#32916930
0"
#32958597
b110001100 #
1"
#33000264
0"
#33041931
b110001101 #
1"
#33083598
0"
#33125265
b110001110 #
1"
#33166932
0"
#33208599
b110001111 #
1"
#33250266
0"
#33291933
b110010000 #
1"
#33333600
0"
#33375267
b110010001 #
1"
#33416934
0"
#33458601
b110010010 #
1"
#33500268
0"
#33541935
b110010011 #
1"
#33583602
0"
#33625269
b110010100 #
1"
#33666936
0"
#33708603
b110010101 #
1"
#33750270
0"
#33791937
b110010110 #
1"
#33833604
0"
#33875271
b110010111 #
1"
#33916938
0"
#33958605
b110011000 #
1"
#34000272
0"
#34041939
b110011001 #
1"
#34083606
0"
#34125273
b110011010 #
1"
#34166940
0"
#34208607
b110011011 #
1"
#34250274
0"
#34291941
b110011100 #
1"
#34333608
0"
#34375275
b110011101 #
1"
#34416942
0"
#34458609
b110011110 #
1"
#34500276
0"
#34541943
b110011111 #
1"
#34583610
0"
#34625277
b110100000 #
1"
#34666944
0"
#34708611
b110100001 #
1"
#34750278
0"
#34791945
b110100010 #
1"
#34833612
0"
#34875279
b110100011 #
1"
#34916946
0"
#34958613
b110100100 #
1"
#35000280
0"
#35041947
b110100101 #
1"
#35083614
0"
#35125281
b110100110 #
1"
#35166948
0"
#35208615
b110100111 #
1"
#35250282
0"
#35291949
b110101000 #
1"
#35333616
0"
#35375283
b110101001 #
1"
#35416950
0"
#35458617
b110101010 #
1"
#35500284
0"
#35541951
b110101011 #
1"
#35583618
0"
#35625285
b110101100 #
1"
#35666952
0"
#35708619
b110101101 #
1"
#35750286
0"
#35791953
b110101110 #
1"
#35833620
0"
#35875287
b110101111 #
1"
#35916954
0"
#35958621
b110110000 #
1"
#36000288
0"
#36041955
b110110001 #
1"
#36083622
0"
#36125289
b110110010 #
1"
#36166956
0"
#36208623
b110110011 #
1"
#36250290
0"
#36291957
b110110100 #
1"
#36333624
0"
#36375291
b110110101 #
1"
#36416958
0"
#36458625
b110110110 #
1"
#36500292
0"
#36541959
b110110111 #
1"
#36583626
0"
#36625293
b110111000 #
1"
#36666960
0"
#36708627
b110111001 #
1"
#36750294
0"
#36791961
b110111010 #
1"
#36833628
0"
#36875295
b110111011 #
1"
#36916962
0"
#36958629
b110111100 #
1"
#37000296
0"
#37041963
b110111101 #
1"
#37083630
0"
#37125297
b110111110 #
1"
#37166964
0"
#37208631
b110111111 #
1"
#37250298
0"
#37291965
b111000000 #
1"
#37333632
0"
#37375299
b111000001 #
1"
#37416966
0"
#37458633
b111000010 #
1"
#37500300
0"
#37541967
b111000011 #
1"
#37583634
0"
#37625301
b111000100 #
1"
#37666968
0"
#37708635
b111000101 #
1"
#37750302
0"
#37791969
b111000110 #
1"
#37833636
0"
#37875303
b111000111 #
1"
#37916970
0"
#37958637
b111001000 #
1"
#38000304
0"
#38041971
b111001001 #
1"
#38083638
0"
#38125305
b111001010 #
1"
#38166972
0"
#38208639
b111001011 #
1"
#38250306
0"
#38291973
b111001100 #
1"
#38333640
0"
#38375307
b111001101 #
1"
#38416974
0"
#38458641
b111001110 #
1"
#38500308
0"
#38541975
b111001111 #
1"
#38583642
0"
#38625309
b111010000 #
1"
#38666976
0"
#38708643
b111010001 #
1"
#38750310
0"
#38791977
b111010010 #
1"
#38833644
0"
#38875311
b111010011 #
1"
#38916978
0"
#38958645
b111010100 #
1"
#39000312
0"
#39041979
b111010101 #
1"
#39083646
0"
#39125313
b111010110 #
1"
#39166980
0"
#39208647
b111010111 #
1"
#39250314
0"
#39291981
b111011000 #
1"
#39333648
0"
#39375315
b111011001 #
1"
#39416982
0"
#39458649
b111011010 #
1"
#39500316
0"
#39541983
b111011011 #
1"
#39583650
0"
#39625317
b111011100 #
1"
#39666984
0"
#39708651
b111011101 #
1"
#39750318
0"
#39791985
b111011110 #
1"
#39833652
0"
#39875319
b111011111 #
1"
#39916986
0"
#39958653
b111100000 #
1"
#40000320
0"
#40041987
b111100001 #
1"
#40083654
0"
#40125321
b111100010 #
1"
#40166988
0"
#40208655
b111100011 #
1"
#40250322
0"
#40291989
b111100100 #
1"
#40333656
0"
#40375323
b111100101 #
1"
#40416990
0"
#40458657
b111100110 #
1"
#40500324
0"
#40541991
b111100111 #
1"
#40583658
0"
#40625325
b111101000 #
1"
#40666992
0"
#40708659
b111101001 #
1"
#40750326
0"
#40791993
b111101010 #
1"
#40833660
0"
#40875327
b111101011 #
1"
#40916994
0"
#40958661
b111101100 #
1"
#41000328
0"
#41041995
b111101101 #
1"
#41083662
0"
#41125329
b111101110 #
1"
#41166996
0"
#41208663
b111101111 #
1"
#41250330
0"
#41291997
b111110000 #
1"
#41333664
0"
#41375331
b111110001 #
1"
#41416998
0"
#41458665
b111110010 #
1"
#41500332
0"
#41541999
b111110011 #
1"
#41583666
0"
#41625333
b111110100 #
1"
#41667000
0"
#41708667
b111110101 #
1"
#41750334
0"
#41792001
b111110110 #
1"
#41833668
0"
#41875335
b111110111 #
1"
#41917002
0"
#41958669
b111111000 #
1"
#42000336
0"
#42042003
b111111001 #
1"
#42083670
0"
#42125337
b111111010 #
1"
#42167004
0"
#42208671
b111111011 #
1"
#42250338
0"
#42292005
b111111100 #
1"
#42333672
0"
#42375339
b111111101 #
1"
#42417006
0"
#42458673
b111111110 #
1"
#42500340
0"
#42542007
b111111111 #
1"
#42583674
0"
#42625341
b1000000000 #
1"
#42667008
0"
#42708675
b1000000001 #
1"
#42750342
0"
#42792009
b1000000010 #
1"
#42833676
0"
#42875343
b1000000011 #
1"
#42917010
0"
#42958677
b1000000100 #
1"
#43000344
0"
#43042011
b1000000101 #
1"
#43083678
0"
#43125345
b1000000110 #
1"
#43167012
0"
#43208679
b1000000111 #
1"
#43250346
0"
#43292013
b1000001000 #
1"
#43333680
0"
#43375347
b1000001001 #
1"
#43417014
0"
#43458681
b1000001010 #
1"
#43500348
0"
#43542015
b1000001011 #
1"
#43583682
0"
#43625349
b1000001100 #
1"
#43667016
0"
#43708683
b1000001101 #
1"
#43750350
0"
#43792017
b1000001110 #
1"
#43833684
0"
#43875351
b1000001111 #
1"
#43917018
0"
#43958685
b1000010000 #
1"
#44000352
0"
#44042019
b1000010001 #
1"
#44083686
0"
#44125353
b1000010010 #
1"
#44167020
0"
#44208687
b1000010011 #
1"
#44250354
0"
#44292021
b1000010100 #
1"
#44333688
0"
#44375355
b1000010101 #
1"
#44417022
0"
#44458689
b1000010110 #
1"
#44500356
0"
#44542023
b1000010111 #
1"
#44583690
0"
#44625357
b1000011000 #
1"
#44667024
0"
#44708691
b1000011001 #
1"
#44750358
0"
#44792025
b1000011010 #
1"
#44833692
0"
#44875359
b1000011011 #
1"
#44917026
0"
#44958693
b1000011100 #
1"
#45000360
0"
#45042027
b1000011101 #
1"
#45083694
0"
#45125361
b1000011110 #
1"
#45167028
0"
#45208695
b1000011111 #
1"
#45250362
0"
#45292029
b1000100000 #
1"
#45333696
0"
#45375363
b1000100001 #
1"
#45417030
0"
#45458697
b1000100010 #
1"
#45500364
0"
#45542031
b1000100011 #
1"
#45583698
0"
#45625365
b1000100100 #
1"
#45667032
0"
#45708699
b1000100101 #
1"
#45750366
0"
#45792033
b1000100110 #
1"
#45833700
0"
#45875367
b1000100111 #
1"
#45917034
0"
#45958701
b1000101000 #
1"
#46000368
0"
#46042035
b1000101001 #
1"
#46083702
0"
#46125369
b1000101010 #
1"
#46167036
0"
#46208703
b1000101011 #
1"
#46250370
0"
#46292037
b1000101100 #
1"
#46333704
0"
#46375371
b1000101101 #
1"
#46417038
0"
#46458705
b1000101110 #
1"
#46500372
0"
#46542039
b1000101111 #
1"
#46583706
0"
#46625373
b1000110000 #
1"
#46667040
0"
#46708707
b1000110001 #
1"
#46750374
0"
#46792041
b1000110010 #
1"
#46833708
0"
#46875375
b1000110011 #
1"
#46917042
0"
#46958709
b1000110100 #
1"
#47000376
0"
#47042043
b1000110101 #
1"
#47083710
0"
#47125377
b1000110110 #
1"
#47167044
0"
#47208711
b1000110111 #
1"
#47250378
0"
#47292045
b1000111000 #
1"
#47333712
0"
#47375379
b1000111001 #
1"
#47417046
0"
#47458713
b1000111010 #
1"
#47500380
0"
#47542047
b1000111011 #
1"
#47583714
0"
#47625381
b1000111100 #
1"
#47667048
0"
#47708715
b1000111101 #
1"
#47750382
0"
#47792049
b1000111110 #
1"
#47833716
0"
#47875383
b1000111111 #
1"
#47917050
0"
#47958717
b1001000000 #
1"
#48000384
0"
#48042051
b1001000001 #
1"
#48083718
0"
#48125385
b1001000010 #
1"
#48167052
0"
#48208719
b1001000011 #
1"
#48250386
0"
#48292053
b1001000100 #
1"
#48333720
0"
#48375387
b1001000101 #
1"
#48417054
0"
#48458721
b1001000110 #
1"
#48500388
0"
#48542055
b1001000111 #
1"
#48583722
0"
#48625389
b1001001000 #
1"
#48667056
0"
#48708723
b1001001001 #
1"
#48750390
0"
#48792057
b1001001010 #
1"
#48833724
0"
#48875391
b1001001011 #
1"
#48917058
0"
#48958725
b1001001100 #
1"
#49000392
0"
#49042059
b1001001101 #
1"
#49083726
0"
#49125393
b1001001110 #
1"
#49167060
0"
#49208727
b1001001111 #
1"
#49250394
0"
#49292061
b1001010000 #
1"
#49333728
0"
#49375395
b1001010001 #
1"
#49417062
0"
#49458729
b1001010010 #
1"
#49500396
0"
#49542063
b1001010011 #
1"
#49583730
0"
#49625397
b1001010100 #
1"
#49667064
0"
#49708731
b1001010101 #
1"
#49750398
0"
#49792065
b1001010110 #
1"
#49833732
0"
#49875399
b1001010111 #
1"
#49917066
0"
#49958733
b1001011000 #
1"
#50000400
0"
#50042067
b1001011001 #
1"
#50083734
0"
#50125401
b1001011010 #
1"
#50167068
0"
#50208735
b1001011011 #
1"
#50250402
0"
#50292069
b1001011100 #
1"
#50333736
0"
#50375403
b1001011101 #
1"
#50417070
0"
#50458737
b1001011110 #
1"
#50500404
0"
#50542071
b1001011111 #
1"
#50583738
0"
#50625405
b1001100000 #
1"
#50667072
0"
#50708739
b1001100001 #
1"
#50750406
0"
#50792073
b1001100010 #
1"
#50833740
0"
#50875407
b1001100011 #
1"
#50917074
0"
#50958741
b1001100100 #
1"
#51000408
0"
#51042075
b1001100101 #
1"
#51083742
0"
#51125409
b1001100110 #
1"
#51167076
0"
#51208743
b1001100111 #
1"
#51250410
0"
#51292077
b1001101000 #
1"
#51333744
0"
#51375411
b1001101001 #
1"
#51417078
0"
#51458745
b1001101010 #
1"
#51500412
0"
#51542079
b1001101011 #
1"
#51583746
0"
#51625413
b1001101100 #
1"
#51667080
0"
#51708747
b1001101101 #
1"
#51750414
0"
#51792081
b1001101110 #
1"
#51833748
0"
#51875415
b1001101111 #
1"
